genpack/genpack.py
genpack-1.0.0.dist-info/METADATA
genpack-1.0.0.dist-info/WHEEL
genpack-1.0.0.dist-info/top_level.txt
genpack-1.0.0.dist-info/RECORD
