Metadata-Version: 2.1
Name: genpack
Version: 1.0.0
Summary: default setup for python
Author: Konoval Evgen
Author-email: zenakonoval6@email.com
